HIV_Isoform_filter/HIV_Isoform_Filtering.py
HIV_Isoform_filter/__init__.py
HIV_Isoform_filter/__main__.py
HIV_Isoform_filter-1.0.2.dist-info/LICENSE.txt
HIV_Isoform_filter-1.0.2.dist-info/METADATA
HIV_Isoform_filter-1.0.2.dist-info/WHEEL
HIV_Isoform_filter-1.0.2.dist-info/entry_points.txt
HIV_Isoform_filter-1.0.2.dist-info/top_level.txt
HIV_Isoform_filter-1.0.2.dist-info/RECORD
