Metadata-Version: 2.1
Name: HIV_Isoform_filter
Version: 1.0.2
Summary: Filters .gtf file of suspected HIV isoforms and confirms the isoform identities
Home-page: 
Author: Jessica Lauren ALbert
Author-email: Jessica Lauren Albert <jessica.albert2001@gmail.com>
License: MIT License
Project-URL: Homepage, https://github.com/JessicaA2019/HIV_Isoform_filter
Keywords: HIV,Isoforms,splicing,ONT sequencing
Classifier: Programming Language :: Python :: 3
Classifier: License :: OSI Approved :: MIT License
Classifier: Operating System :: OS Independent
Requires-Python: >=3.11
License-File: LICENSE.txt
